{
  "date": "2026-07-11",
  "snapshots": [
    {
      "t": "00:27",
      "ts": 1783697266,
      "score": 50,
      "temp": 23,
      "prices": {
        "^KS11": NaN,
        "^KQ11": NaN,
        "NVDA": 208.62,
        "^N225": 67743.85,
        "^VIX": 15.66,
        "^BSESN": 77569.39,
        "CL=F": 71.35,
        "000001.SS": 3996.16,
        "AAPL": 313.57,
        "^TWII": 45354.61,
        "^RUT": 2968.63,
        "TSLA": 409.73,
        "^HSI": 24175.12,
        "GC=F": 4110.0,
        "MSFT": 382.7,
        "^STOXX50E": 6259.71,
        "^GDAXI": 25035.23,
        "247540.KQ": NaN,
        "^TNX": 4.553,
        "086520.KQ": NaN,
        "006400.KS": NaN,
        "005380.KS": NaN,
        "^DJI": 52630.02,
        "SOXX": 580.2,
        "373220.KS": NaN,
        "012450.KS": NaN,
        "028260.KS": NaN,
        "000270.KS": NaN,
        "^GSPC": 7559.8,
        "402340.KS": NaN,
        "196170.KQ": NaN,
        "KRW=X": 1500.67,
        "000660.KS": NaN,
        "068270.KS": NaN,
        "009150.KS": NaN,
        "028300.KQ": NaN,
        "207940.KS": NaN,
        "005930.KS": NaN,
        "086790.KS": NaN,
        "^FTSE": 10488.48,
        "^FCHI": 8314.44,
        "105560.KS": NaN,
        "055550.KS": NaN,
        "034020.KS": NaN,
        "058470.KQ": NaN,
        "035420.KS": NaN,
        "035720.KS": NaN,
        "^IXIC": 26227.94,
        "^SSMI": 14224.36,
        "009540.KS": NaN,
        "329180.KS": NaN,
        "NQ=F": 29933.0
      }
    },
    {
      "t": "02:04",
      "ts": 1783703056,
      "score": 76,
      "temp": 25,
      "prices": {
        "^VIX": 15.24,
        "^KS11": NaN,
        "^KQ11": NaN,
        "NVDA": 209.51,
        "402340.KS": NaN,
        "000660.KS": NaN,
        "009150.KS": NaN,
        "005930.KS": NaN,
        "028260.KS": NaN,
        "247540.KQ": NaN,
        "005380.KS": NaN,
        "086520.KQ": NaN,
        "058470.KQ": NaN,
        "006400.KS": NaN,
        "196170.KQ": NaN,
        "000270.KS": NaN,
        "^N225": 67743.85,
        "CL=F": 71.15,
        "068270.KS": NaN,
        "TSLA": 411.54,
        "373220.KS": NaN,
        "028300.KQ": NaN,
        "034020.KS": NaN,
        "207940.KS": NaN,
        "035420.KS": NaN,
        "035720.KS": NaN,
        "329180.KS": NaN,
        "012450.KS": NaN,
        "000001.SS": NaN,
        "^BSESN": 77569.39,
        "009540.KS": NaN,
        "086790.KS": NaN,
        "^TWII": 45354.61,
        "105560.KS": NaN,
        "^HSI": 24030.18,
        "055550.KS": NaN,
        "^RUT": 2974.91,
        "AAPL": 314.6,
        "^TNX": 4.561,
        "GC=F": 4115.7,
        "MSFT": 385.74,
        "NQ=F": 30021.5,
        "^GSPC": 7562.47,
        "^DJI": 52610.87,
        "^FTSE": 10497.29,
        "^STOXX50E": 6269.97,
        "SOXX": 580.48,
        "^GDAXI": 25067.09,
        "^IXIC": 26254.06,
        "^FCHI": 8338.97,
        "^SSMI": 14235.09,
        "KRW=X": 1501.98
      }
    },
    {
      "t": "02:17",
      "ts": 1783703833,
      "score": 80,
      "temp": 25,
      "prices": {
        "^KS11": NaN,
        "^KQ11": NaN,
        "NVDA": 209.73,
        "^VIX": 15.32,
        "402340.KS": NaN,
        "000660.KS": NaN,
        "009150.KS": NaN,
        "005930.KS": NaN,
        "028260.KS": NaN,
        "005380.KS": NaN,
        "247540.KQ": NaN,
        "058470.KQ": NaN,
        "086520.KQ": NaN,
        "006400.KS": NaN,
        "000270.KS": NaN,
        "196170.KQ": NaN,
        "034020.KS": NaN,
        "^N225": 67743.85,
        "CL=F": 71.13,
        "068270.KS": NaN,
        "373220.KS": NaN,
        "028300.KQ": NaN,
        "009540.KS": NaN,
        "207940.KS": NaN,
        "035420.KS": NaN,
        "035720.KS": NaN,
        "329180.KS": NaN,
        "012450.KS": NaN,
        "000001.SS": NaN,
        "^BSESN": 77569.39,
        "086790.KS": NaN,
        "^TWII": 45354.61,
        "105560.KS": NaN,
        "055550.KS": NaN,
        "^HSI": 24030.18,
        "TSLA": 409.35,
        "AAPL": 314.35,
        "^TNX": 4.563,
        "^RUT": 2976.67,
        "GC=F": 4112.1,
        "^GSPC": 7565.47,
        "^DJI": 52641.84,
        "NQ=F": 30013.25,
        "^FTSE": 10497.29,
        "^STOXX50E": 6269.97,
        "MSFT": 385.15,
        "^GDAXI": 25067.09,
        "^IXIC": 26256.54,
        "^FCHI": 8338.97,
        "KRW=X": 1501.21,
        "^SSMI": 14235.09,
        "SOXX": 581.97
      }
    },
    {
      "t": "03:48",
      "ts": 1783709300,
      "score": 78,
      "temp": 25,
      "prices": {
        "^VIX": 15.27,
        "^KS11": NaN,
        "^KQ11": NaN,
        "NVDA": 209.95,
        "402340.KS": NaN,
        "000660.KS": NaN,
        "009150.KS": NaN,
        "028260.KS": NaN,
        "005930.KS": NaN,
        "005380.KS": NaN,
        "247540.KQ": NaN,
        "058470.KQ": NaN,
        "086520.KQ": NaN,
        "006400.KS": NaN,
        "000270.KS": NaN,
        "196170.KQ": NaN,
        "^N225": 67743.85,
        "034020.KS": NaN,
        "068270.KS": NaN,
        "028300.KQ": NaN,
        "373220.KS": NaN,
        "009540.KS": NaN,
        "207940.KS": NaN,
        "329180.KS": NaN,
        "035420.KS": NaN,
        "035720.KS": NaN,
        "086790.KS": NaN,
        "105560.KS": NaN,
        "CL=F": 71.55,
        "055550.KS": NaN,
        "^TNX": 4.569,
        "TSLA": 408.65,
        "^GSPC": 7572.19,
        "000001.SS": NaN,
        "^TWII": 45354.61,
        "^HSI": 24030.18,
        "GC=F": 4110.7,
        "^RUT": 2981.04,
        "^DJI": 52677.62,
        "NQ=F": 30035.5,
        "^BSESN": 76741.82,
        "AAPL": 315.29,
        "^IXIC": 26278.82,
        "MSFT": 385.38,
        "^FTSE": 10497.29,
        "^STOXX50E": 6269.97,
        "^GDAXI": 25067.09,
        "012450.KS": NaN,
        "SOXX": 580.62,
        "KRW=X": 1500.67,
        "^FCHI": 8338.97,
        "^SSMI": 14235.09
      }
    },
    {
      "t": "05:07",
      "ts": 1783714073,
      "score": 82,
      "temp": 25,
      "prices": {
        "^VIX": 15.02,
        "^KS11": NaN,
        "^KQ11": NaN,
        "NVDA": 210.96,
        "402340.KS": NaN,
        "000660.KS": NaN,
        "009150.KS": NaN,
        "005930.KS": NaN,
        "028260.KS": NaN,
        "005380.KS": NaN,
        "247540.KQ": NaN,
        "058470.KQ": NaN,
        "086520.KQ": NaN,
        "006400.KS": NaN,
        "196170.KQ": NaN,
        "000270.KS": NaN,
        "068270.KS": NaN,
        "028300.KQ": NaN,
        "^N225": 67743.85,
        "207940.KS": NaN,
        "034020.KS": NaN,
        "009540.KS": NaN,
        "329180.KS": NaN,
        "373220.KS": NaN,
        "035420.KS": NaN,
        "035720.KS": NaN,
        "086790.KS": NaN,
        "105560.KS": NaN,
        "055550.KS": NaN,
        "^TNX": 4.569,
        "CL=F": 71.62,
        "^GSPC": 7575.39,
        "^RUT": 2981.08,
        "000001.SS": NaN,
        "^TWII": 45354.61,
        "^HSI": 24030.18,
        "GC=F": 4115.1,
        "012450.KS": NaN,
        "NQ=F": 30040.5,
        "^BSESN": 76741.82,
        "TSLA": 407.76,
        "^IXIC": 26281.61,
        "^DJI": 52637.01,
        "AAPL": 315.32,
        "^FTSE": 10497.29,
        "^STOXX50E": 6269.97,
        "KRW=X": 1500.13,
        "^GDAXI": 25067.09,
        "MSFT": 385.1,
        "^FCHI": 8338.97,
        "^SSMI": 14235.09,
        "SOXX": 581.34
      }
    },
    {
      "t": "06:17",
      "ts": 1783718262,
      "score": 83,
      "temp": 25,
      "prices": {
        "^VIX": 15.03,
        "^KS11": NaN,
        "^KQ11": NaN,
        "NVDA": 210.96,
        "402340.KS": NaN,
        "000660.KS": NaN,
        "009150.KS": NaN,
        "005930.KS": NaN,
        "028260.KS": NaN,
        "005380.KS": NaN,
        "247540.KQ": NaN,
        "058470.KQ": NaN,
        "086520.KQ": NaN,
        "006400.KS": NaN,
        "196170.KQ": NaN,
        "000270.KS": NaN,
        "068270.KS": NaN,
        "028300.KQ": NaN,
        "^N225": 67743.85,
        "207940.KS": NaN,
        "034020.KS": NaN,
        "009540.KS": NaN,
        "329180.KS": NaN,
        "373220.KS": NaN,
        "035420.KS": NaN,
        "035720.KS": NaN,
        "086790.KS": NaN,
        "105560.KS": NaN,
        "CL=F": 71.51,
        "055550.KS": NaN,
        "^TNX": 4.569,
        "^RUT": 2977.81,
        "^GSPC": 7575.39,
        "000001.SS": NaN,
        "^TWII": 45354.61,
        "^HSI": 24030.18,
        "NQ=F": 30068.5,
        "012450.KS": NaN,
        "^BSESN": 76741.82,
        "KRW=X": 1498.87,
        "TSLA": 407.76,
        "^IXIC": 26281.61,
        "^DJI": 52637.01,
        "AAPL": 315.32,
        "^FTSE": 10497.29,
        "^STOXX50E": 6269.97,
        "^GDAXI": 25067.09,
        "MSFT": 385.1,
        "^FCHI": 8338.97,
        "^SSMI": 14235.09,
        "SOXX": 581.34,
        "GC=F": 4128.9
      }
    }
  ]
}